{
    "company": {
      "name": "Натяжные потолки Иркутск",
      "logo": "/img/logo-crop.png"
    },
    "navigation": 
      {
        "header1": "Натяжные потолки",
        "header2": "Пятый элемент уюта",
        "img": "/img/bg-img-main.jpg",
        "alt": "picture"
      },

      "bannerLeft": 
      {
        "img": "/img/gift-icon.svg",
        "text": "Точечный светильник в подарок за каждые 2 м² потолка",
        "alt": "picture"
      },

      "swiperSlides": {
        "title": "Swiper",
        "items": [
          {
            "title": "Комната красивая номер один ",
            "description": "Наш новый потолок 10 кв.м",
            "img": "/img/swiper/swiper1.jpg",
            "alt": "swiper1"
          },
          {
            "title": "Комната красивая номер два ",
            "description": "Наш второй новый потолок 20 кв.м",
            "img": "/img/swiper/swiper2.jpg",
            "alt": "swiper2"
          },
          {
            "title": "Комната красивая номер три ",
            "description": "Наш третий новый потолок 30 кв.м",
            "img": "/img/swiper/swiper3.jpg",
            "alt": "swiper3"
          },
          {
            "title": "Комната красивая номер четыре ",
            "description": "Наш четвертый новый потолок 40 кв.м",
            "img": "/img/swiper/swiper4.jpg",
            "alt": "swiper4"
          }
        ]
      },

      "bannerRight": 
      {
        "head": "Звоните",
        "phone": "8(495)762-94-68",
        "text": "C 9:00 до 21:00 пн-вс"
      },


    "promo": {
      "text": "Закажите натяжной потолок - получите второй в подарок! Бесплатно",
      "textSmall": "Все подробности по телефон 8 (495) 762-94-68",
      "textPromoBlock": ""
    },

    "workSection": {
        "headerText": "Как мы работаем?",
        "items": [
          {
            "id": "1",
            "title": "Оставляете заявку на выезд замещика",
            "description": "",
            "img": "",
            "alt": ""
          },
          {
            "id": "2",
            "title": "Выезд мастера в день подачи заявки",
            "img": "",
            "description": "",
            "alt": ""
          },
          {
            "id": "3",
            "title": "Наше приемущество - вы вносите 10 % оплаты",
            "img": "",
            "description": "",
            "alt": ""
          },
          {
            "id": "4",
            "title": "Демонстируем каталог и снимаем замеры",
            "img": "",
            "description": "",
            "alt": ""
          },
          {
            "id": "5",
            "title": "Монтируем потолок (2-3 часа)",
            "img": "",
            "description": "",
            "alt": ""
          }
        ]

      },

      "advantagesSection": {
        "headerText": "Почему мы?",
        "items": [
          {
            
            "title": "7 лет успешной работы",
            "description": "",
            "img": "/img/thumb-icon.svg",
            "alt": "work1",
            "href": "feedback"
          },
          {
          
            "title": "Монтаж 2-3 часа",
            "img": "/img/clock-icon.svg",
            "description": "Монтаж осуществляется без нагрева и с использованием полимерно-композитных газовых балонов. Взрывоопасность таких баллонов стремится к нулю.",
            "alt": "work2",
            "href": "#"
          },
          {
           
            "title": "Гарантия 15 лет на материал ",
            "img": "/img/clock-icon.svg",
            "description": "Используем только качественные натяжные потолки ведущих производителей: Clipso, Cerutti, Descor. Такие потолет отличаются прочностью и экологичностью. Поэтому мы уверены — вам не придется обращаться за гарантийным ремонтом.",
            "alt": "work3",
            "href": "#"
          },
          {
           
            "title": "Уборка после монтажа",
            "img": "/img/woman-icon.png",
            "description": "",
            "alt": "work4",
            "href": ""
          },
          {
           
            "title": "Предоплата всего 10%",
            "img": "/img/moneybox-icon.png",
            "description": "",
            "alt": "work5",
            "href": ""
          }
        ]
      },

      "input-section": {
        "first-text": "Ваш адрес",
        "second-text": "Ваш телефон",
        "button-text": "Вызвать замерщика"
      },

      "calculate-section": {
        "header-text": "Рассчитать стоимость потолка",
        "first-text": "Классический ",
        "second-text": "Многоуровневый",
        "third-text": "Звездный",
        "fourth-text": "Комбинированный",
        "total-text": "Примерная стоимость"
      },

      "feedbackSlides": {
        "title": "Отзывы",
        "items": [
          {
            "title": "1 Lorem ipsum dolor sit amet, consectetur adipiscing elit. Aenean accumsan maximus hendrerit. Donec molestie libero non enim ullamcorper, quis malesuada leo",
            "description": "Наталья г. Москва",
            "alt": "swiper1"
          },
          {
            "title": "2 Lorem ipsum dolor sit amet, consectetur adipiscing elit. Aenean accumsan maximus hendrerit. Donec molestie libero non enim ullamcorper, quis malesuada leo",
            "description": "Елена г. Иркутск",
            "alt": "swiper2"
          },
          {
            "title": "3 Lorem ipsum dolor sit amet, consectetur adipiscing elit. Aenean accumsan maximus hendrerit. Donec molestie libero non enim ullamcorper, quis malesuada leo",
            "description": "Татьяна г. Калининград",
            "alt": "swiper3"
          },
          {
            "title": "4 Lorem ipsum dolor sit amet, consectetur adipiscing elit. Aenean accumsan maximus hendrerit. Donec molestie libero non enim ullamcorper, quis malesuada leo",
            "description": "Виктория г. Сочи",
            "alt": "swiper4"
          }
        ]
      },

      "footerSection": {
        "footerText": "Создать уют в доме просто, как позвонить",
        "footerPhone": "8 (495) 762-94-68"
      }
    }